anime_muip/__init__.py
anime_muip/__main__.py
anime_muip-0.1.dist-info/LICENSE
anime_muip-0.1.dist-info/WHEEL
anime_muip-0.1.dist-info/METADATA
anime_muip-0.1.dist-info/RECORD
