Metadata-Version: 2.1
Name: anime-muip
Version: 0.1
Summary: Simple module for anime game servers
License: GNU GPL v3
Author: MrM0der
Author-email: 124781355+MrM0der@users.noreply.github.com
Requires-Python: >=3.10,<4.0
Classifier: License :: Other/Proprietary License
Classifier: Programming Language :: Python :: 3
Classifier: Programming Language :: Python :: 3.10
